{
  "$schema": "https://vega.github.io/schema/vega-lite/v4.json",
  "width": 500,
  "height": 300,
  "title": "CO2 Emissions (metric tons per capita)",
  "data": {
    "url": "https://raw.githubusercontent.com/andrew-cao/FIT3179/main/data/dataset.csv"
  },
  "transform": [
    {"filter": "datum.co2_emissions > 0 & datum.life_expectancy > 0"}
  ],
  "layer": [
    {
      "mark": {"type": "circle", "color": "#78c679"},
      "encoding": {
        "x": {
          "field": "co2_emissions",
          "title": "CO2 Emissions (metric tons per capita, log scale)",
          "type": "quantitative",
          "scale": {"type": "log"},
          "axis": {"grid": false}
        },
        "y": {
          "field": "life_expectancy",
          "title": "Life expectancy",
          "type": "quantitative",
          "axis": {"grid": false}
        },
        "tooltip": [
          {"field": "Country", "type": "nominal"},
          {
            "field": "life_expectancy",
            "title": "Life expectancy",
            "type": "quantitative"
          },
          {
            "field": "co2_emissions",
            "title": "CO2 Emissions",
            "type": "quantitative"
          }
        ]
      }
    }
  ],
  "config": {}
}